graphics/__init__.py
graphics/function/Calculate.py
graphics/function/Classifier.py
graphics/function/DeepLab.py
graphics/function/Detection.py
graphics/function/Evaluate.py
graphics/function/FaceDetector.py
graphics/function/FaceRecognition.py
graphics/function/FontWriter.py
graphics/function/Format.py
graphics/function/Graphics.py
graphics/function/ImageCrop.py
graphics/function/InsightFace.py
graphics/function/MachineLearning.py
graphics/function/Matting.py
graphics/function/MtcnnDetector.py
graphics/function/OcrDetector.py
graphics/function/Retrieval.py
graphics/function/Segmentation.py
graphics/function/VideoCodec.py
graphics/function/VideoProcess.py
graphics/function/Watermark.py
graphics/function/__init__.py
graphics/libs/__init__.py
graphics/libs/basnet.py
graphics/libs/cbam_resnet.py
graphics/libs/common.py
graphics/libs/download.py
graphics/libs/f3net.py
graphics/libs/face_align.py
graphics/libs/logger.py
graphics/libs/model_store.py
graphics/libs/network.py
graphics/libs/resnet_model.py
graphics/libs/se_resnet.py
graphics/libs/se_resnext.py
graphics/libs/snapshot.py
graphics/libs/craft/__init__.py
graphics/libs/craft/craft.py
graphics/libs/craft/craft_utils.py
graphics/libs/craft/refinenet.py
graphics/libs/craft/vgg16_bn.py
graphics/libs/indexnet/__init__.py
graphics/libs/indexnet/batchnorm.py
graphics/libs/indexnet/comm.py
graphics/libs/indexnet/hlaspp.py
graphics/libs/indexnet/hlconv.py
graphics/libs/indexnet/hldecoder.py
graphics/libs/indexnet/hlindex.py
graphics/libs/indexnet/hlmobilenetv2.py
graphics/libs/indexnet/modelsummary.py
graphics/libs/mtcnn/__init__.py
graphics/libs/mtcnn/box_utils.py
graphics/libs/mtcnn/first_stage.py
graphics/libs/mtcnn/get_nets.py
graphics/libs/retrieval/__init__.py
graphics/libs/retrieval/aggregator.py
graphics/libs/retrieval/augmentation.py
graphics/libs/retrieval/dataset.py
graphics/libs/retrieval/evaluate.py
graphics/libs/retrieval/extract.py
graphics/libs/retrieval/metric.py
graphics/libs/retrieval/reduction.py
ai_graphics-0.1.48.dist-info/METADATA
ai_graphics-0.1.48.dist-info/WHEEL
ai_graphics-0.1.48.dist-info/top_level.txt
ai_graphics-0.1.48.dist-info/zip-safe
ai_graphics-0.1.48.dist-info/RECORD
