Metadata-Version: 2.1
Name: ai-graphics
Version: 0.1.48
Summary: AI Graphics Toolkit
Home-page: https://github.com/CachCheng/Python_Cookbook
Author: CachCheng
Author-email: tkggpdc2007@163.com
License: Apache-2.0
Platform: UNKNOWN
Requires-Dist: numpy
Requires-Dist: opencv-python
Requires-Dist: flask
Requires-Dist: tezign
Requires-Dist: sklearn
Requires-Dist: scenedetect
Requires-Dist: moviepy (==1.0.0)
Requires-Dist: Pillow (<7.0.0)
Requires-Dist: torch
Requires-Dist: torchvision
Requires-Dist: joblib
